pyscf/tblis_einsum/libtblis_einsum.so
pyscf/tblis_einsum/__init__.py
pyscf/tblis_einsum/libtci.so
pyscf/tblis_einsum/libtblis.so
pyscf/tblis_einsum/tblis_einsum.py
pyscf_tblis.libs/libatomic-35750833.so.1.0.0
pyscf_tblis.libs/libgomp-a34b3233.so.1.0.0
pyscf_tblis-0.1.1.dist-info/LICENSE
pyscf_tblis-0.1.1.dist-info/RECORD
pyscf_tblis-0.1.1.dist-info/top_level.txt
pyscf_tblis-0.1.1.dist-info/METADATA
pyscf_tblis-0.1.1.dist-info/WHEEL
